{
  "id": "3ec36759-0c33-4df8-aa7c-a0af5bb9a5d1",
  "prevId": "666031cd-be8c-471a-8514-c8a5bc7c5227",
  "version": "7",
  "dialect": "postgresql",
  "tables": {
    "public.account": {
      "name": "account",
      "schema": "",
      "columns": {
        "id": {
          "name": "id",
          "type": "text",
          "primaryKey": true,
          "notNull": true
        },
        "accountId": {
          "name": "accountId",
          "type": "text",
          "primaryKey": false,
          "notNull": true
        },
        "providerId": {
          "name": "providerId",
          "type": "text",
          "primaryKey": false,
          "notNull": true
        },
        "userId": {
          "name": "userId",
          "type": "text",
          "primaryKey": false,
          "notNull": true
        },
        "accessToken": {
          "name": "accessToken",
          "type": "text",
          "primaryKey": false,
          "notNull": false
        },
        "refreshToken": {
          "name": "refreshToken",
          "type": "text",
          "primaryKey": false,
          "notNull": false
        },
        "idToken": {
          "name": "idToken",
          "type": "text",
          "primaryKey": false,
          "notNull": false
        },
        "expiresAt": {
          "name": "expiresAt",
          "type": "timestamp",
          "primaryKey": false,
          "notNull": false
        },
        "accessTokenExpiresAt": {
          "name": "accessTokenExpiresAt",
          "type": "timestamp",
          "primaryKey": false,
          "notNull": false
        },
        "refreshTokenExpiresAt": {
          "name": "refreshTokenExpiresAt",
          "type": "timestamp",
          "primaryKey": false,
          "notNull": false
        },
        "scope": {
          "name": "scope",
          "type": "text",
          "primaryKey": false,
          "notNull": false
        },
        "password": {
          "name": "password",
          "type": "text",
          "primaryKey": false,
          "notNull": false
        },
        "createdAt": {
          "name": "createdAt",
          "type": "timestamp",
          "primaryKey": false,
          "notNull": true,
          "default": "now()"
        },
        "updatedAt": {
          "name": "updatedAt",
          "type": "timestamp",
          "primaryKey": false,
          "notNull": true,
          "default": "now()"
        }
      },
      "indexes": {
        "account_user_id_idx": {
          "name": "account_user_id_idx",
          "columns": [
            {
              "expression": "userId",
              "isExpression": false,
              "asc": true,
              "nulls": "last"
            }
          ],
          "isUnique": false,
          "concurrently": false,
          "method": "btree",
          "with": {}
        },
        "account_provider_idx": {
          "name": "account_provider_idx",
          "columns": [
            {
              "expression": "providerId",
              "isExpression": false,
              "asc": true,
              "nulls": "last"
            },
            {
              "expression": "accountId",
              "isExpression": false,
              "asc": true,
              "nulls": "last"
            }
          ],
          "isUnique": false,
          "concurrently": false,
          "method": "btree",
          "with": {}
        }
      },
      "foreignKeys": {
        "account_userId_user_id_fk": {
          "name": "account_userId_user_id_fk",
          "tableFrom": "account",
          "tableTo": "user",
          "columnsFrom": [
            "userId"
          ],
          "columnsTo": [
            "id"
          ],
          "onDelete": "cascade",
          "onUpdate": "no action"
        }
      },
      "compositePrimaryKeys": {},
      "uniqueConstraints": {},
      "policies": {},
      "checkConstraints": {},
      "isRLSEnabled": false
    },
    "public.session": {
      "name": "session",
      "schema": "",
      "columns": {
        "id": {
          "name": "id",
          "type": "text",
          "primaryKey": true,
          "notNull": true
        },
        "expiresAt": {
          "name": "expiresAt",
          "type": "timestamp",
          "primaryKey": false,
          "notNull": true
        },
        "token": {
          "name": "token",
          "type": "text",
          "primaryKey": false,
          "notNull": true
        },
        "ipAddress": {
          "name": "ipAddress",
          "type": "text",
          "primaryKey": false,
          "notNull": false
        },
        "userAgent": {
          "name": "userAgent",
          "type": "text",
          "primaryKey": false,
          "notNull": false
        },
        "userId": {
          "name": "userId",
          "type": "text",
          "primaryKey": false,
          "notNull": true
        },
        "createdAt": {
          "name": "createdAt",
          "type": "timestamp",
          "primaryKey": false,
          "notNull": true,
          "default": "now()"
        },
        "updatedAt": {
          "name": "updatedAt",
          "type": "timestamp",
          "primaryKey": false,
          "notNull": true,
          "default": "now()"
        }
      },
      "indexes": {
        "session_user_id_idx": {
          "name": "session_user_id_idx",
          "columns": [
            {
              "expression": "userId",
              "isExpression": false,
              "asc": true,
              "nulls": "last"
            }
          ],
          "isUnique": false,
          "concurrently": false,
          "method": "btree",
          "with": {}
        },
        "session_expires_at_idx": {
          "name": "session_expires_at_idx",
          "columns": [
            {
              "expression": "expiresAt",
              "isExpression": false,
              "asc": true,
              "nulls": "last"
            }
          ],
          "isUnique": false,
          "concurrently": false,
          "method": "btree",
          "with": {}
        },
        "session_token_idx": {
          "name": "session_token_idx",
          "columns": [
            {
              "expression": "token",
              "isExpression": false,
              "asc": true,
              "nulls": "last"
            }
          ],
          "isUnique": false,
          "concurrently": false,
          "method": "btree",
          "with": {}
        }
      },
      "foreignKeys": {
        "session_userId_user_id_fk": {
          "name": "session_userId_user_id_fk",
          "tableFrom": "session",
          "tableTo": "user",
          "columnsFrom": [
            "userId"
          ],
          "columnsTo": [
            "id"
          ],
          "onDelete": "cascade",
          "onUpdate": "no action"
        }
      },
      "compositePrimaryKeys": {},
      "uniqueConstraints": {
        "session_token_unique": {
          "name": "session_token_unique",
          "nullsNotDistinct": false,
          "columns": [
            "token"
          ]
        }
      },
      "policies": {},
      "checkConstraints": {},
      "isRLSEnabled": false
    },
    "public.user": {
      "name": "user",
      "schema": "",
      "columns": {
        "id": {
          "name": "id",
          "type": "text",
          "primaryKey": true,
          "notNull": true
        },
        "name": {
          "name": "name",
          "type": "text",
          "primaryKey": false,
          "notNull": true
        },
        "email": {
          "name": "email",
          "type": "text",
          "primaryKey": false,
          "notNull": true
        },
        "emailVerified": {
          "name": "emailVerified",
          "type": "boolean",
          "primaryKey": false,
          "notNull": true,
          "default": false
        },
        "image": {
          "name": "image",
          "type": "text",
          "primaryKey": false,
          "notNull": false
        },
        "createdAt": {
          "name": "createdAt",
          "type": "timestamp",
          "primaryKey": false,
          "notNull": true,
          "default": "now()"
        },
        "updatedAt": {
          "name": "updatedAt",
          "type": "timestamp",
          "primaryKey": false,
          "notNull": true,
          "default": "now()"
        },
        "onboardingCompleted": {
          "name": "onboardingCompleted",
          "type": "boolean",
          "primaryKey": false,
          "notNull": true,
          "default": false
        }
      },
      "indexes": {},
      "foreignKeys": {},
      "compositePrimaryKeys": {},
      "uniqueConstraints": {
        "user_email_unique": {
          "name": "user_email_unique",
          "nullsNotDistinct": false,
          "columns": [
            "email"
          ]
        }
      },
      "policies": {},
      "checkConstraints": {},
      "isRLSEnabled": false
    },
    "public.verification": {
      "name": "verification",
      "schema": "",
      "columns": {
        "id": {
          "name": "id",
          "type": "text",
          "primaryKey": true,
          "notNull": true
        },
        "identifier": {
          "name": "identifier",
          "type": "text",
          "primaryKey": false,
          "notNull": true
        },
        "value": {
          "name": "value",
          "type": "text",
          "primaryKey": false,
          "notNull": true
        },
        "expiresAt": {
          "name": "expiresAt",
          "type": "timestamp",
          "primaryKey": false,
          "notNull": true
        },
        "createdAt": {
          "name": "createdAt",
          "type": "timestamp",
          "primaryKey": false,
          "notNull": true,
          "default": "now()"
        },
        "updatedAt": {
          "name": "updatedAt",
          "type": "timestamp",
          "primaryKey": false,
          "notNull": true,
          "default": "now()"
        }
      },
      "indexes": {
        "verification_identifier_idx": {
          "name": "verification_identifier_idx",
          "columns": [
            {
              "expression": "identifier",
              "isExpression": false,
              "asc": true,
              "nulls": "last"
            }
          ],
          "isUnique": false,
          "concurrently": false,
          "method": "btree",
          "with": {}
        },
        "verification_expires_at_idx": {
          "name": "verification_expires_at_idx",
          "columns": [
            {
              "expression": "expiresAt",
              "isExpression": false,
              "asc": true,
              "nulls": "last"
            }
          ],
          "isUnique": false,
          "concurrently": false,
          "method": "btree",
          "with": {}
        }
      },
      "foreignKeys": {},
      "compositePrimaryKeys": {},
      "uniqueConstraints": {},
      "policies": {},
      "checkConstraints": {},
      "isRLSEnabled": false
    },
    "public.bazi_charts": {
      "name": "bazi_charts",
      "schema": "",
      "columns": {
        "id": {
          "name": "id",
          "type": "uuid",
          "primaryKey": true,
          "notNull": true,
          "default": "gen_random_uuid()"
        },
        "profile_id": {
          "name": "profile_id",
          "type": "uuid",
          "primaryKey": false,
          "notNull": true
        },
        "year_pillar": {
          "name": "year_pillar",
          "type": "varchar(100)",
          "primaryKey": false,
          "notNull": true
        },
        "month_pillar": {
          "name": "month_pillar",
          "type": "varchar(100)",
          "primaryKey": false,
          "notNull": true
        },
        "day_pillar": {
          "name": "day_pillar",
          "type": "varchar(100)",
          "primaryKey": false,
          "notNull": true
        },
        "hour_pillar": {
          "name": "hour_pillar",
          "type": "varchar(100)",
          "primaryKey": false,
          "notNull": false
        },
        "day_master": {
          "name": "day_master",
          "type": "varchar(50)",
          "primaryKey": false,
          "notNull": true
        },
        "primary_element": {
          "name": "primary_element",
          "type": "varchar(50)",
          "primaryKey": false,
          "notNull": true
        },
        "element_strength": {
          "name": "element_strength",
          "type": "varchar(500)",
          "primaryKey": false,
          "notNull": true
        },
        "created_at": {
          "name": "created_at",
          "type": "timestamp",
          "primaryKey": false,
          "notNull": true,
          "default": "now()"
        }
      },
      "indexes": {
        "bazi_charts_profile_id_idx": {
          "name": "bazi_charts_profile_id_idx",
          "columns": [
            {
              "expression": "profile_id",
              "isExpression": false,
              "asc": true,
              "nulls": "last"
            }
          ],
          "isUnique": false,
          "concurrently": false,
          "method": "btree",
          "with": {}
        }
      },
      "foreignKeys": {
        "bazi_charts_profile_id_birth_profiles_id_fk": {
          "name": "bazi_charts_profile_id_birth_profiles_id_fk",
          "tableFrom": "bazi_charts",
          "tableTo": "birth_profiles",
          "columnsFrom": [
            "profile_id"
          ],
          "columnsTo": [
            "id"
          ],
          "onDelete": "no action",
          "onUpdate": "no action"
        }
      },
      "compositePrimaryKeys": {},
      "uniqueConstraints": {
        "bazi_charts_profile_id_unique": {
          "name": "bazi_charts_profile_id_unique",
          "nullsNotDistinct": false,
          "columns": [
            "profile_id"
          ]
        }
      },
      "policies": {},
      "checkConstraints": {},
      "isRLSEnabled": false
    },
    "public.birth_profiles": {
      "name": "birth_profiles",
      "schema": "",
      "columns": {
        "id": {
          "name": "id",
          "type": "uuid",
          "primaryKey": true,
          "notNull": true,
          "default": "gen_random_uuid()"
        },
        "user_id": {
          "name": "user_id",
          "type": "text",
          "primaryKey": false,
          "notNull": true
        },
        "birth_date": {
          "name": "birth_date",
          "type": "timestamp",
          "primaryKey": false,
          "notNull": true
        },
        "birth_hour": {
          "name": "birth_hour",
          "type": "integer",
          "primaryKey": false,
          "notNull": false
        },
        "birth_time_period": {
          "name": "birth_time_period",
          "type": "varchar(50)",
          "primaryKey": false,
          "notNull": false
        },
        "gender": {
          "name": "gender",
          "type": "varchar(10)",
          "primaryKey": false,
          "notNull": true
        },
        "is_time_unknown": {
          "name": "is_time_unknown",
          "type": "boolean",
          "primaryKey": false,
          "notNull": false,
          "default": false
        },
        "created_at": {
          "name": "created_at",
          "type": "timestamp",
          "primaryKey": false,
          "notNull": true,
          "default": "now()"
        },
        "updated_at": {
          "name": "updated_at",
          "type": "timestamp",
          "primaryKey": false,
          "notNull": true,
          "default": "now()"
        }
      },
      "indexes": {
        "birth_profiles_user_id_idx": {
          "name": "birth_profiles_user_id_idx",
          "columns": [
            {
              "expression": "user_id",
              "isExpression": false,
              "asc": true,
              "nulls": "last"
            }
          ],
          "isUnique": false,
          "concurrently": false,
          "method": "btree",
          "with": {}
        }
      },
      "foreignKeys": {
        "birth_profiles_user_id_user_id_fk": {
          "name": "birth_profiles_user_id_user_id_fk",
          "tableFrom": "birth_profiles",
          "tableTo": "user",
          "columnsFrom": [
            "user_id"
          ],
          "columnsTo": [
            "id"
          ],
          "onDelete": "no action",
          "onUpdate": "no action"
        }
      },
      "compositePrimaryKeys": {},
      "uniqueConstraints": {},
      "policies": {},
      "checkConstraints": {},
      "isRLSEnabled": false
    },
    "public.thai_astrology_data": {
      "name": "thai_astrology_data",
      "schema": "",
      "columns": {
        "id": {
          "name": "id",
          "type": "uuid",
          "primaryKey": true,
          "notNull": true,
          "default": "gen_random_uuid()"
        },
        "profile_id": {
          "name": "profile_id",
          "type": "uuid",
          "primaryKey": false,
          "notNull": true
        },
        "day": {
          "name": "day",
          "type": "varchar(50)",
          "primaryKey": false,
          "notNull": true
        },
        "color": {
          "name": "color",
          "type": "varchar(100)",
          "primaryKey": false,
          "notNull": true
        },
        "planet": {
          "name": "planet",
          "type": "varchar(100)",
          "primaryKey": false,
          "notNull": true
        },
        "buddha_position": {
          "name": "buddha_position",
          "type": "varchar(200)",
          "primaryKey": false,
          "notNull": true
        },
        "personality": {
          "name": "personality",
          "type": "varchar(500)",
          "primaryKey": false,
          "notNull": true
        },
        "lucky_number": {
          "name": "lucky_number",
          "type": "integer",
          "primaryKey": false,
          "notNull": true
        },
        "lucky_direction": {
          "name": "lucky_direction",
          "type": "varchar(100)",
          "primaryKey": false,
          "notNull": true
        },
        "created_at": {
          "name": "created_at",
          "type": "timestamp",
          "primaryKey": false,
          "notNull": true,
          "default": "now()"
        }
      },
      "indexes": {
        "thai_astrology_profile_id_idx": {
          "name": "thai_astrology_profile_id_idx",
          "columns": [
            {
              "expression": "profile_id",
              "isExpression": false,
              "asc": true,
              "nulls": "last"
            }
          ],
          "isUnique": false,
          "concurrently": false,
          "method": "btree",
          "with": {}
        }
      },
      "foreignKeys": {
        "thai_astrology_data_profile_id_birth_profiles_id_fk": {
          "name": "thai_astrology_data_profile_id_birth_profiles_id_fk",
          "tableFrom": "thai_astrology_data",
          "tableTo": "birth_profiles",
          "columnsFrom": [
            "profile_id"
          ],
          "columnsTo": [
            "id"
          ],
          "onDelete": "no action",
          "onUpdate": "no action"
        }
      },
      "compositePrimaryKeys": {},
      "uniqueConstraints": {
        "thai_astrology_data_profile_id_unique": {
          "name": "thai_astrology_data_profile_id_unique",
          "nullsNotDistinct": false,
          "columns": [
            "profile_id"
          ]
        }
      },
      "policies": {},
      "checkConstraints": {},
      "isRLSEnabled": false
    },
    "public.chart_narratives": {
      "name": "chart_narratives",
      "schema": "",
      "columns": {
        "id": {
          "name": "id",
          "type": "uuid",
          "primaryKey": true,
          "notNull": true,
          "default": "gen_random_uuid()"
        },
        "profile_id": {
          "name": "profile_id",
          "type": "uuid",
          "primaryKey": false,
          "notNull": true
        },
        "structured_reading": {
          "name": "structured_reading",
          "type": "text",
          "primaryKey": false,
          "notNull": true
        },
        "updated_at": {
          "name": "updated_at",
          "type": "timestamp",
          "primaryKey": false,
          "notNull": false
        },
        "created_at": {
          "name": "created_at",
          "type": "timestamp",
          "primaryKey": false,
          "notNull": true,
          "default": "now()"
        }
      },
      "indexes": {
        "chart_narratives_profile_idx": {
          "name": "chart_narratives_profile_idx",
          "columns": [
            {
              "expression": "profile_id",
              "isExpression": false,
              "asc": true,
              "nulls": "last"
            }
          ],
          "isUnique": false,
          "concurrently": false,
          "method": "btree",
          "with": {}
        }
      },
      "foreignKeys": {
        "chart_narratives_profile_id_birth_profiles_id_fk": {
          "name": "chart_narratives_profile_id_birth_profiles_id_fk",
          "tableFrom": "chart_narratives",
          "tableTo": "birth_profiles",
          "columnsFrom": [
            "profile_id"
          ],
          "columnsTo": [
            "id"
          ],
          "onDelete": "no action",
          "onUpdate": "no action"
        }
      },
      "compositePrimaryKeys": {},
      "uniqueConstraints": {
        "chart_narratives_profile_id_unique": {
          "name": "chart_narratives_profile_id_unique",
          "nullsNotDistinct": false,
          "columns": [
            "profile_id"
          ]
        }
      },
      "policies": {},
      "checkConstraints": {},
      "isRLSEnabled": false
    },
    "public.compatibility": {
      "name": "compatibility",
      "schema": "",
      "columns": {
        "id": {
          "name": "id",
          "type": "uuid",
          "primaryKey": true,
          "notNull": true,
          "default": "gen_random_uuid()"
        },
        "profile_a_id": {
          "name": "profile_a_id",
          "type": "uuid",
          "primaryKey": false,
          "notNull": true
        },
        "profile_b_id": {
          "name": "profile_b_id",
          "type": "uuid",
          "primaryKey": false,
          "notNull": true
        },
        "score": {
          "name": "score",
          "type": "integer",
          "primaryKey": false,
          "notNull": true
        },
        "element_harmony": {
          "name": "element_harmony",
          "type": "integer",
          "primaryKey": false,
          "notNull": false
        },
        "branch_harmony": {
          "name": "branch_harmony",
          "type": "integer",
          "primaryKey": false,
          "notNull": false
        },
        "analysis": {
          "name": "analysis",
          "type": "text",
          "primaryKey": false,
          "notNull": true
        },
        "strengths": {
          "name": "strengths",
          "type": "varchar(2000)",
          "primaryKey": false,
          "notNull": false
        },
        "challenges": {
          "name": "challenges",
          "type": "varchar(2000)",
          "primaryKey": false,
          "notNull": false
        },
        "share_token": {
          "name": "share_token",
          "type": "varchar(100)",
          "primaryKey": false,
          "notNull": false
        },
        "created_at": {
          "name": "created_at",
          "type": "timestamp",
          "primaryKey": false,
          "notNull": true,
          "default": "now()"
        }
      },
      "indexes": {
        "compatibility_profile_a_idx": {
          "name": "compatibility_profile_a_idx",
          "columns": [
            {
              "expression": "profile_a_id",
              "isExpression": false,
              "asc": true,
              "nulls": "last"
            }
          ],
          "isUnique": false,
          "concurrently": false,
          "method": "btree",
          "with": {}
        },
        "compatibility_profile_b_idx": {
          "name": "compatibility_profile_b_idx",
          "columns": [
            {
              "expression": "profile_b_id",
              "isExpression": false,
              "asc": true,
              "nulls": "last"
            }
          ],
          "isUnique": false,
          "concurrently": false,
          "method": "btree",
          "with": {}
        },
        "compatibility_share_token_idx": {
          "name": "compatibility_share_token_idx",
          "columns": [
            {
              "expression": "share_token",
              "isExpression": false,
              "asc": true,
              "nulls": "last"
            }
          ],
          "isUnique": false,
          "concurrently": false,
          "method": "btree",
          "with": {}
        }
      },
      "foreignKeys": {
        "compatibility_profile_a_id_birth_profiles_id_fk": {
          "name": "compatibility_profile_a_id_birth_profiles_id_fk",
          "tableFrom": "compatibility",
          "tableTo": "birth_profiles",
          "columnsFrom": [
            "profile_a_id"
          ],
          "columnsTo": [
            "id"
          ],
          "onDelete": "no action",
          "onUpdate": "no action"
        },
        "compatibility_profile_b_id_birth_profiles_id_fk": {
          "name": "compatibility_profile_b_id_birth_profiles_id_fk",
          "tableFrom": "compatibility",
          "tableTo": "birth_profiles",
          "columnsFrom": [
            "profile_b_id"
          ],
          "columnsTo": [
            "id"
          ],
          "onDelete": "no action",
          "onUpdate": "no action"
        }
      },
      "compositePrimaryKeys": {},
      "uniqueConstraints": {
        "compatibility_share_token_unique": {
          "name": "compatibility_share_token_unique",
          "nullsNotDistinct": false,
          "columns": [
            "share_token"
          ]
        }
      },
      "policies": {},
      "checkConstraints": {},
      "isRLSEnabled": false
    },
    "public.daily_readings": {
      "name": "daily_readings",
      "schema": "",
      "columns": {
        "id": {
          "name": "id",
          "type": "uuid",
          "primaryKey": true,
          "notNull": true,
          "default": "gen_random_uuid()"
        },
        "profile_id": {
          "name": "profile_id",
          "type": "uuid",
          "primaryKey": false,
          "notNull": true
        },
        "date": {
          "name": "date",
          "type": "date",
          "primaryKey": false,
          "notNull": true
        },
        "content": {
          "name": "content",
          "type": "text",
          "primaryKey": false,
          "notNull": true
        },
        "lucky_number": {
          "name": "lucky_number",
          "type": "integer",
          "primaryKey": false,
          "notNull": false
        },
        "lucky_color": {
          "name": "lucky_color",
          "type": "varchar(100)",
          "primaryKey": false,
          "notNull": false
        },
        "lucky_direction": {
          "name": "lucky_direction",
          "type": "varchar(100)",
          "primaryKey": false,
          "notNull": false
        },
        "element_energy": {
          "name": "element_energy",
          "type": "varchar(500)",
          "primaryKey": false,
          "notNull": false
        },
        "created_at": {
          "name": "created_at",
          "type": "timestamp",
          "primaryKey": false,
          "notNull": true,
          "default": "now()"
        }
      },
      "indexes": {
        "daily_readings_profile_date_idx": {
          "name": "daily_readings_profile_date_idx",
          "columns": [
            {
              "expression": "profile_id",
              "isExpression": false,
              "asc": true,
              "nulls": "last"
            },
            {
              "expression": "date",
              "isExpression": false,
              "asc": true,
              "nulls": "last"
            }
          ],
          "isUnique": false,
          "concurrently": false,
          "method": "btree",
          "with": {}
        }
      },
      "foreignKeys": {
        "daily_readings_profile_id_birth_profiles_id_fk": {
          "name": "daily_readings_profile_id_birth_profiles_id_fk",
          "tableFrom": "daily_readings",
          "tableTo": "birth_profiles",
          "columnsFrom": [
            "profile_id"
          ],
          "columnsTo": [
            "id"
          ],
          "onDelete": "no action",
          "onUpdate": "no action"
        }
      },
      "compositePrimaryKeys": {},
      "uniqueConstraints": {},
      "policies": {},
      "checkConstraints": {},
      "isRLSEnabled": false
    },
    "public.compatibility_invite": {
      "name": "compatibility_invite",
      "schema": "",
      "columns": {
        "id": {
          "name": "id",
          "type": "uuid",
          "primaryKey": true,
          "notNull": true,
          "default": "gen_random_uuid()"
        },
        "token": {
          "name": "token",
          "type": "text",
          "primaryKey": false,
          "notNull": true
        },
        "inviter_id": {
          "name": "inviter_id",
          "type": "text",
          "primaryKey": false,
          "notNull": true
        },
        "inviter_name": {
          "name": "inviter_name",
          "type": "text",
          "primaryKey": false,
          "notNull": true
        },
        "inviter_profile_id": {
          "name": "inviter_profile_id",
          "type": "uuid",
          "primaryKey": false,
          "notNull": true
        },
        "is_used": {
          "name": "is_used",
          "type": "boolean",
          "primaryKey": false,
          "notNull": true,
          "default": false
        },
        "used_by": {
          "name": "used_by",
          "type": "text",
          "primaryKey": false,
          "notNull": false
        },
        "used_at": {
          "name": "used_at",
          "type": "timestamp",
          "primaryKey": false,
          "notNull": false
        },
        "created_at": {
          "name": "created_at",
          "type": "timestamp",
          "primaryKey": false,
          "notNull": true,
          "default": "now()"
        },
        "expires_at": {
          "name": "expires_at",
          "type": "timestamp",
          "primaryKey": false,
          "notNull": true
        }
      },
      "indexes": {
        "compatibility_invite_token_idx": {
          "name": "compatibility_invite_token_idx",
          "columns": [
            {
              "expression": "token",
              "isExpression": false,
              "asc": true,
              "nulls": "last"
            }
          ],
          "isUnique": false,
          "concurrently": false,
          "method": "btree",
          "with": {}
        },
        "compatibility_invite_inviter_idx": {
          "name": "compatibility_invite_inviter_idx",
          "columns": [
            {
              "expression": "inviter_id",
              "isExpression": false,
              "asc": true,
              "nulls": "last"
            }
          ],
          "isUnique": false,
          "concurrently": false,
          "method": "btree",
          "with": {}
        },
        "compatibility_invite_expires_at_idx": {
          "name": "compatibility_invite_expires_at_idx",
          "columns": [
            {
              "expression": "expires_at",
              "isExpression": false,
              "asc": true,
              "nulls": "last"
            }
          ],
          "isUnique": false,
          "concurrently": false,
          "method": "btree",
          "with": {}
        }
      },
      "foreignKeys": {
        "compatibility_invite_inviter_id_user_id_fk": {
          "name": "compatibility_invite_inviter_id_user_id_fk",
          "tableFrom": "compatibility_invite",
          "tableTo": "user",
          "columnsFrom": [
            "inviter_id"
          ],
          "columnsTo": [
            "id"
          ],
          "onDelete": "cascade",
          "onUpdate": "no action"
        },
        "compatibility_invite_inviter_profile_id_birth_profiles_id_fk": {
          "name": "compatibility_invite_inviter_profile_id_birth_profiles_id_fk",
          "tableFrom": "compatibility_invite",
          "tableTo": "birth_profiles",
          "columnsFrom": [
            "inviter_profile_id"
          ],
          "columnsTo": [
            "id"
          ],
          "onDelete": "cascade",
          "onUpdate": "no action"
        },
        "compatibility_invite_used_by_user_id_fk": {
          "name": "compatibility_invite_used_by_user_id_fk",
          "tableFrom": "compatibility_invite",
          "tableTo": "user",
          "columnsFrom": [
            "used_by"
          ],
          "columnsTo": [
            "id"
          ],
          "onDelete": "set null",
          "onUpdate": "no action"
        }
      },
      "compositePrimaryKeys": {},
      "uniqueConstraints": {
        "compatibility_invite_token_unique": {
          "name": "compatibility_invite_token_unique",
          "nullsNotDistinct": false,
          "columns": [
            "token"
          ]
        }
      },
      "policies": {},
      "checkConstraints": {},
      "isRLSEnabled": false
    }
  },
  "enums": {},
  "schemas": {},
  "sequences": {},
  "roles": {},
  "policies": {},
  "views": {},
  "_meta": {
    "columns": {},
    "schemas": {},
    "tables": {}
  }
}